commondatamodel_objectmodel_cdmstandards/__init__.py
commondatamodel_objectmodel_cdmstandards/cdmstandards.py
commondatamodel_objectmodel_cdmstandards/schema_documents/foundations.1.0.cdm.json
commondatamodel_objectmodel_cdmstandards/schema_documents/foundations.1.1.cdm.json
commondatamodel_objectmodel_cdmstandards/schema_documents/foundations.1.2.cdm.json
commondatamodel_objectmodel_cdmstandards/schema_documents/foundations.2.0.cdm.json
commondatamodel_objectmodel_cdmstandards/schema_documents/foundations.2.1.1.cdm.json
commondatamodel_objectmodel_cdmstandards/schema_documents/foundations.2.1.cdm.json
commondatamodel_objectmodel_cdmstandards/schema_documents/foundations.3.0.cdm.json
commondatamodel_objectmodel_cdmstandards/schema_documents/foundations.3.1.cdm.json
commondatamodel_objectmodel_cdmstandards/schema_documents/foundations.4.0.cdm.json
commondatamodel_objectmodel_cdmstandards/schema_documents/foundations.4.1.cdm.json
commondatamodel_objectmodel_cdmstandards/schema_documents/foundations.4.2.cdm.json
commondatamodel_objectmodel_cdmstandards/schema_documents/foundations.4.3.cdm.json
commondatamodel_objectmodel_cdmstandards/schema_documents/foundations.4.4.cdm.json
commondatamodel_objectmodel_cdmstandards/schema_documents/foundations.4.5.cdm.json
commondatamodel_objectmodel_cdmstandards/schema_documents/foundations.4.6.cdm.json
commondatamodel_objectmodel_cdmstandards/schema_documents/foundations.4.7.cdm.json
commondatamodel_objectmodel_cdmstandards/schema_documents/foundations.cdm.json
commondatamodel_objectmodel_cdmstandards/schema_documents/meanings.1.0.cdm.json
commondatamodel_objectmodel_cdmstandards/schema_documents/meanings.1.1.cdm.json
commondatamodel_objectmodel_cdmstandards/schema_documents/meanings.1.2.1.cdm.json
commondatamodel_objectmodel_cdmstandards/schema_documents/meanings.1.2.cdm.json
commondatamodel_objectmodel_cdmstandards/schema_documents/meanings.calendar.1.0.cdm.json
commondatamodel_objectmodel_cdmstandards-2.8.0.dist-info/METADATA
commondatamodel_objectmodel_cdmstandards-2.8.0.dist-info/WHEEL
commondatamodel_objectmodel_cdmstandards-2.8.0.dist-info/top_level.txt
commondatamodel_objectmodel_cdmstandards-2.8.0.dist-info/RECORD
