Metadata-Version: 2.1
Name: commondatamodel-objectmodel-cdmstandards
Version: 2.8.0
Summary: The Common Data Model standard schema and entities
Home-page: https://github.com/microsoft/CDM/tree/master/objectModel/Python
Author: Microsoft
Author-email: UNKNOWN
License: UNKNOWN
Platform: UNKNOWN
Classifier: Programming Language :: Python :: 3.5
Classifier: License :: OSI Approved :: MIT License
Classifier: Operating System :: OS Independent
